myrich/__init__.py
myrich/__main__.py
myrich/_version.py
myrich/shell.py
myrich/vendor/__init__.py
myrich/vendor/delegator.py
myrich-0.2.2.dist-info/LICENSE
myrich-0.2.2.dist-info/METADATA
myrich-0.2.2.dist-info/WHEEL
myrich-0.2.2.dist-info/entry_points.txt
myrich-0.2.2.dist-info/top_level.txt
myrich-0.2.2.dist-info/RECORD
