Metadata-Version: 2.1
Name: myrich
Version: 0.2.2
Summary: Shell-like using Rich for render rich text content
Home-page: https://github.com/oleksis/myrich
Author: Oleksis Fraga
Author-email: oleksis.fraga@gmail.com
License: MIT
Keywords: render rich text syntax highlighting markdown terminal console
Platform: UNKNOWN
Classifier: Topic :: Terminals
Classifier: Development Status :: 5 - Production/Stable
Classifier: Environment :: Console
Classifier: License :: OSI Approved :: MIT License
Classifier: Intended Audience :: Developers
Classifier: Operating System :: Microsoft :: Windows
Classifier: Operating System :: MacOS
Classifier: Operating System :: POSIX :: Linux
Classifier: Programming Language :: Python
Classifier: Programming Language :: Python :: 3.6
Classifier: Programming Language :: Python :: 3.7
Classifier: Programming Language :: Python :: 3.8
Classifier: Programming Language :: Python :: Implementation
Classifier: Programming Language :: Python :: Implementation :: CPython
Requires-Python: >=3.6.1
Requires-Dist: rich (>=7.0.0)
